{"client":"Thunder Client","collectionName":"catadoption","dateExported":"2022-07-28T15:02:44.610Z","version":"1.1","folders":[{"_id":"a7b0016c-709f-4edb-9c76-c3e4543c1971","name":"base","containerId":"","created":"2022-07-04T15:01:05.041Z","sortNum":10000},{"_id":"eb29b5d9-6be2-4d4b-8d80-207c2fa3a89d","name":"auth","containerId":"","created":"2022-07-04T15:01:05.042Z","sortNum":20000},{"_id":"6492b412-098f-497e-bc43-9493b875131a","name":"cats","containerId":"","created":"2022-07-28T14:27:43.182Z","sortNum":30000},{"_id":"5760d6d5-b999-45a0-82e3-1a4e059b3f78","name":"shelters","containerId":"","created":"2022-07-28T14:32:00.352Z","sortNum":40000}],"requests":[{"_id":"49901be7-b0e0-470b-b7c4-2e7408b055b4","colId":"671465ad-3b2a-4449-8900-9b8b2e100bf3","containerId":"a7b0016c-709f-4edb-9c76-c3e4543c1971","name":"get root","url":"{{URL}}","method":"GET","sortNum":10000,"created":"2022-07-04T15:01:05.042Z","modified":"2022-07-07T10:43:06.476Z","headers":[],"params":[],"tests":[{"type":"res-code","custom":"","action":"equal","value":"200"},{"type":"res-body","custom":"","action":"equal","value":"Hello World!"}]},{"_id":"557c3921-2fc4-4cbb-b929-291087d8ad86","colId":"671465ad-3b2a-4449-8900-9b8b2e100bf3","containerId":"a7b0016c-709f-4edb-9c76-c3e4543c1971","name":"http://localhost:3033/health","url":"http://localhost:3033/health","method":"GET","sortNum":20000,"created":"2022-07-04T15:01:05.043Z","modified":"2022-07-04T15:01:05.043Z","headers":[],"params":[],"tests":[]},{"_id":"d74c72c6-6fc1-4855-b8f2-11be74195b63","colId":"671465ad-3b2a-4449-8900-9b8b2e100bf3","containerId":"eb29b5d9-6be2-4d4b-8d80-207c2fa3a89d","name":"login as admin","url":"{{URL}}/auth/login","method":"POST","sortNum":38750,"created":"2022-07-04T15:01:05.045Z","modified":"2022-07-04T17:06:42.301Z","headers":[],"params":[],"body":{"type":"json","raw":"{\n  \"username\": \"{{ADMIN_USER}}\",\n  \"password\": \"{{ADMIN_PASSWORD}}\"\n}","form":[]},"tests":[{"type":"res-code","custom":"","action":"equal","value":"201"},{"type":"json-query","custom":"json.","action":"isjson","value":"1"},{"type":"set-env-var","custom":"json.access_token","action":"setto","value":"{{JWT}}"}]},{"_id":"02799a7b-a792-47fe-8d69-e652c939041f","colId":"671465ad-3b2a-4449-8900-9b8b2e100bf3","containerId":"eb29b5d9-6be2-4d4b-8d80-207c2fa3a89d","name":"add user as admin","url":"http://localhost:3033/users","method":"POST","sortNum":44375,"created":"2022-07-04T15:01:05.044Z","modified":"2022-07-07T11:25:02.015Z","headers":[],"params":[],"body":{"type":"json","raw":"{\n    \"name\":\"{{NEW_USER}}\",\n    \"password\":\"{{NEW_PASSWORD}}\",\n    \"roles\":[\"user\"]\n}","form":[]},"auth":{"type":"bearer","bearer":"{{JWT}}"},"tests":[{"type":"set-env-var","custom":"json.id","action":"setto","value":"{{CREATED_USER_ID}}"},{"type":"res-code","custom":"","action":"equal","value":"201"}]},{"_id":"7fc320ed-0871-40f2-9886-79b06801b576","colId":"671465ad-3b2a-4449-8900-9b8b2e100bf3","containerId":"eb29b5d9-6be2-4d4b-8d80-207c2fa3a89d","name":"get Users as admin","url":"{{URL}}/users","method":"GET","sortNum":45781.3,"created":"2022-07-04T15:01:05.046Z","modified":"2022-07-07T11:38:54.886Z","headers":[],"params":[],"auth":{"type":"bearer","bearer":"{{JWT}}"},"tests":[{"type":"res-code","custom":"","action":"equal","value":"200"}]},{"_id":"2df9a134-c7ce-4402-83a9-4f67ddac6a8d","colId":"671465ad-3b2a-4449-8900-9b8b2e100bf3","containerId":"eb29b5d9-6be2-4d4b-8d80-207c2fa3a89d","name":"login as user","url":"{{URL}}/auth/login","method":"POST","sortNum":47187.5,"created":"2022-07-07T11:38:19.025Z","modified":"2022-07-07T11:39:26.390Z","headers":[],"params":[],"body":{"type":"json","raw":"{\n  \"username\": \"{{NEW_USER}}\",\n  \"password\": \"{{NEW_PASSWORD}}\"\n}","form":[]},"tests":[{"type":"res-code","custom":"","action":"equal","value":"201"},{"type":"json-query","custom":"json.","action":"isjson","value":"1"},{"type":"set-env-var","custom":"json.access_token","action":"setto","value":"{{JWT}}"}]},{"_id":"24f0bec1-0106-4ede-b95a-79d209d959be","colId":"671465ad-3b2a-4449-8900-9b8b2e100bf3","containerId":"eb29b5d9-6be2-4d4b-8d80-207c2fa3a89d","name":"delete user as user","url":"{{URL}}/users/{{CREATED_USER_ID}}","method":"DELETE","sortNum":60000,"created":"2022-07-04T15:01:05.047Z","modified":"2022-07-07T12:05:55.298Z","headers":[],"params":[],"auth":{"type":"bearer","bearer":"{{JWT}}"},"tests":[{"type":"res-code","custom":"","action":"equal","value":"403"}]},{"_id":"e182ba3c-21aa-42f4-a8ac-708749c38ff6","colId":"671465ad-3b2a-4449-8900-9b8b2e100bf3","containerId":"eb29b5d9-6be2-4d4b-8d80-207c2fa3a89d","name":"login as admin again","url":"{{URL}}/auth/login","method":"POST","sortNum":65000,"created":"2022-07-07T11:40:28.136Z","modified":"2022-07-07T11:40:35.205Z","headers":[],"params":[],"body":{"type":"json","raw":"{\n  \"username\": \"{{ADMIN_USER}}\",\n  \"password\": \"{{ADMIN_PASSWORD}}\"\n}","form":[]},"tests":[{"type":"res-code","custom":"","action":"equal","value":"201"},{"type":"json-query","custom":"json.","action":"isjson","value":"1"},{"type":"set-env-var","custom":"json.access_token","action":"setto","value":"{{JWT}}"}]},{"_id":"1dd9184a-9ec5-4c55-87f4-7675b251e7a8","colId":"671465ad-3b2a-4449-8900-9b8b2e100bf3","containerId":"eb29b5d9-6be2-4d4b-8d80-207c2fa3a89d","name":"delete user as admin","url":"{{URL}}/users/{{CREATED_USER_ID}}","method":"DELETE","sortNum":70000,"created":"2022-07-07T11:40:09.011Z","modified":"2022-07-07T12:41:33.741Z","headers":[],"params":[],"auth":{"type":"bearer","bearer":"{{JWT}}"},"tests":[{"type":"res-body","custom":"","action":"contains","value":"acknowledged"}]},{"_id":"502d9e33-5cac-411d-8005-4644490e28d4","colId":"671465ad-3b2a-4449-8900-9b8b2e100bf3","containerId":"6492b412-098f-497e-bc43-9493b875131a","name":"upload image","url":"{{URL}}/cats/62e29ed92a5b89582fe08c06/upload","method":"POST","sortNum":80000,"created":"2022-07-28T14:27:49.784Z","modified":"2022-07-28T14:39:46.868Z","headers":[],"params":[],"body":{"type":"formdata","raw":"","form":[],"files":[{"name":"file","value":"/run/user/1000/doc/eb44975/anova-irm-accumulating-evidence-1920x1080.jpg"}]},"tests":[]},{"_id":"70720606-f0e0-4d1f-b460-6e9b6cd72247","colId":"671465ad-3b2a-4449-8900-9b8b2e100bf3","containerId":"6492b412-098f-497e-bc43-9493b875131a","name":"add cat","url":"{{URL}}/cats","method":"POST","sortNum":90000,"created":"2022-07-28T14:27:59.743Z","modified":"2022-07-28T14:36:06.528Z","headers":[],"params":[],"body":{"type":"json","raw":"{\n    \"name\":\"Minou\",\n    \"age\": 20,\n    \"breed\":\"Main Coon\",\n    \"shelter\":\"62e29ebc2a5b89582fe08c03\"\n}","form":[]},"auth":{"type":"bearer","bearer":"{{JWT}}"},"tests":[]},{"_id":"7bf9ca85-7f17-468d-8879-e28e7effdfc9","colId":"671465ad-3b2a-4449-8900-9b8b2e100bf3","containerId":"6492b412-098f-497e-bc43-9493b875131a","name":"get cats","url":"{{URL}}/cats","method":"GET","sortNum":100000,"created":"2022-07-28T14:28:05.594Z","modified":"2022-07-28T14:38:44.949Z","headers":[],"params":[],"tests":[]},{"_id":"59d11ccd-1503-4106-950b-14da9c7369ec","colId":"671465ad-3b2a-4449-8900-9b8b2e100bf3","containerId":"5760d6d5-b999-45a0-82e3-1a4e059b3f78","name":"add shelter","url":"{{URL}}/shelters","method":"POST","sortNum":110000,"created":"2022-07-28T14:32:10.172Z","modified":"2022-07-28T14:35:26.809Z","headers":[],"params":[],"body":{"type":"json","raw":"{\n    \"name\":\"Cute Cat Shelter\",\n    \"address\":{\n        \"street\":\"Cute Cat Street 4\",\n        \"zip\":28201\n    },\n    \"contact\":{\n        \"email\": \"cute@catsshelter.com\"\n    }\n}","form":[]},"auth":{"type":"bearer","bearer":"{{JWT}}"},"tests":[]},{"_id":"4b9238cc-3e05-44a9-9a15-69ff9537f703","colId":"671465ad-3b2a-4449-8900-9b8b2e100bf3","containerId":"5760d6d5-b999-45a0-82e3-1a4e059b3f78","name":"add shelter","url":"{{URL}}/shelters","method":"GET","sortNum":120000,"created":"2022-07-28T14:32:49.094Z","modified":"2022-07-28T14:32:49.094Z","headers":[],"params":[],"auth":{"type":"bearer","bearer":"{{JWT}}"},"tests":[]}],"settings":{"headers":[],"auth":{"type":"bearer"},"tests":[],"envId":"edd7f073-1737-4496-9e87-bd88b74383d8"}}
